zipstream_ai/.github /workflows/draft-pdf.yml
zipstream_ai/__init__.py
zipstream_ai/cli.py
zipstream_ai/file_parser.py
zipstream_ai/llm_query_engine.py
zipstream_ai/stream_reader.py
zipstream_ai-1.0.1.dist-info/METADATA
zipstream_ai-1.0.1.dist-info/WHEEL
zipstream_ai-1.0.1.dist-info/entry_points.txt
zipstream_ai-1.0.1.dist-info/RECORD
